<?xml version="1.0" encoding="UTF-8" ?>
<odoo>

    <record id="medical_encounter_view_form" model="ir.ui.view">
        <field name="name">medical.encounter.form</field>
        <field name="model">medical.encounter</field>
        <field name="inherit_id"
               ref="pos_validation.medical_encounter_view_form"/>
        <field name="arch" type="xml">
            <xpath expr="//div[@name='button_box']" position="inside">
                <button type="action"
                        name="%(medical_encounter_medication_action)s"
                        context="{'default_medical_id': active_id}"
                        class="oe_stat_button" icon="fa-pills"
                        string="Add Medication"/>
            </xpath>
            <notebook position="inside">
                <page name="medication" string="Medication">
                    <field name="medication_item_ids"/>
                </page>
            </notebook>
        </field>
    </record>

    <record id="medical_medication_item_view_form" model="ir.ui.view">
        <field name="name">medical.medication.item.form</field>
        <field name="model">medical.medication.item</field>
        <field name="arch" type="xml">
            <form create="0">
                <group>
                    <field name="encounter_id"/>
                    <field name="location_id"/>
                    <field name="product_id"/>
                    <field name="qty"/>
                    <field name="price"/>
                </group>
            </form>
        </field>
    </record>

    <record id="medical_medication_item_view_tree" model="ir.ui.view">
        <field name="name">medical.medication.item.tree</field>
        <field name="model">medical.medication.item</field>
        <field name="arch" type="xml">
            <tree editable="bottom">
                    <field name="product_id"/>
                    <field name="qty"/>
                    <field name="price"/>
                    <field name="location_id"/>
            </tree>
        </field>
    </record>

</odoo>
