<?xml version="1.0" encoding="utf-8" ?>
<odoo>

    <record id="edit_holiday_new" model="ir.ui.view">
        <field name="name">Leave Request - Add full day + hide nº of days +
            show related readonly
        </field>
        <field name="model">hr.holidays</field>
        <field name="inherit_id" ref="hr_holidays.edit_holiday_new"/>
        <field name="arch" type="xml">
            <field name="department_id" position="attributes">
                <attribute name="readonly">1</attribute>
            </field>
            <field name="date_from" position="before">
                <field name="count_in_hours" invisible="1"/>
                <field name="date_from_full"
                       attrs="{'required':[('type', '=', 'remove')], 'invisible': [('count_in_hours', '=', True)]}"
                       class="oe_inline"/>
            </field>
            <field name="date_from" position="attributes">
                <attribute name="attrs">{'required':[('type', '=', 'remove')],
                    'invisible': [('count_in_hours', '=', False)]}
                </attribute>
            </field>
            <field name="date_to" position="before">
                <field name="date_to_full"
                       attrs="{'required':[('type', '=', 'remove')], 'invisible': [('count_in_hours', '=', True)]}"
                       class="oe_inline"/>
            </field>
            <field name="date_to" position="attributes">
                <attribute name="attrs">{'required':[('type', '=', 'remove')],
                    'invisible': [('count_in_hours', '=', False)]}
                </attribute>
            </field>
            <field name="holiday_status_id" position="attributes">
                <attribute name="options">{'no_create': True, "no_open": True}</attribute>
            </field>
            <xpath expr="//field[@name='number_of_days_temp']/.."
                   position="before">
                <field name="count_in_hours" invisible="1"/>
            </xpath>
            <xpath expr="//field[@name='number_of_days_temp']/.."
                   position="attributes">
                <attribute name="attrs">{'invisible': [('count_in_hours', '=',
                    True)]}
                </attribute>
            </xpath>
            <xpath expr="//field[@name='number_of_days_temp']/.."
                   position="after">
                <div attrs="{'invisible': [('count_in_hours', '=', False)]}">
                    <field name="number_of_hours_temp" class="oe_inline"/>
                    hours
                </div>
            </xpath>
            <field name="holiday_type" position="attributes">
                <attribute name="invisible">1</attribute>
            </field>
        </field>
    </record>

    <record id="view_hr_holidays_filter" model="ir.ui.view">
        <field name="name">hr.holidays.filter</field>
        <field name="model">hr.holidays</field>
        <field name="inherit_id" ref="hr_holidays.view_hr_holidays_filter"/>
        <field name="arch" type="xml">
            <filter name="group_category" position="attributes">
                <attribute name="invisible">1</attribute>
            </filter>
            <filter name="group_second_approver_id" position="attributes">
                <attribute name="invisible">1</attribute>
            </filter>
            <filter name="todo" position="attributes">
                <attribute name="invisible">1</attribute>
            </filter>
            <filter name="gray" position="attributes">
                <attribute name="invisible">1</attribute>
            </filter>
            <filter name="my_team_leaves" position="attributes">
                <attribute name="invisible">1</attribute>
            </filter>
        </field>
    </record>

    <!-- Time description changes-->

    <record id="view_holiday" model="ir.ui.view">
        <field name="name">hr.holidays.report_tree</field>
        <field name="model">hr.holidays</field>
        <field name="inherit_id" ref="hr_holidays.view_holiday"/>
        <field name="arch" type="xml">
            <field name="number_of_days" position="attributes">
                <attribute name="invisible">1</attribute>
            </field>
            <field name="number_of_days" position="after">
                <field name="time_description"/>
            </field>
        </field>
    </record>

    <record id="view_holiday_allocation_tree_inherit_leave_hours" model="ir.ui.view">
        <field name="model">hr.holidays</field>
        <field name="inherit_id" ref="hr_holidays.view_holiday_allocation_tree"/>
        <field name="arch" type="xml">
            <field name="number_of_days" position="attributes">
                <attribute name="invisible">1</attribute>
            </field>
            <field name="number_of_days" position="after">
                <field name="time_description"/>
            </field>
        </field>
    </record>

    <record id="view_hr_holidays_kanban" model="ir.ui.view">
        <field name="model">hr.holidays</field>
        <field name="inherit_id" ref="hr_holidays.view_hr_holidays_kanban"/>
        <field name="arch" type="xml">
            <field name="number_of_days" position="replace">
                <field name="time_description"/>
            </field>
            <xpath expr="//t[@t-esc='record.number_of_days.value']/.." position="replace">
                <span class="badge"><t t-esc="record.time_description.value"/></span>
            </xpath>
        </field>
    </record>

    <record id="view_holiday_employee" model="ir.ui.view">
        <field name="name">hr.holidays.report_tree</field>
        <field name="model">hr.holidays</field>
        <field name="inherit_id" ref="hr_holidays.view_holiday_employee"/>
        <field name="arch" type="xml">
            <field name="number_of_days" position="replace">
                <field name="time_description"/>
            </field>
        </field>
    </record>

    <record id="view_holiday_simple" model="ir.ui.view">
        <field name="name">hr.holidays.report_tree</field>
        <field name="model">hr.holidays</field>
        <field name="inherit_id" ref="hr_holidays.view_holiday_simple"/>
        <field name="arch" type="xml">
            <field name="number_of_days" position="replace">
                <field name="time_description"/>
            </field>
        </field>
    </record>


</odoo>
